batch_bridge/__init__.py
batch_bridge/_base.py
batch_bridge/_openai.py
batch_bridge/errors.py
batch_bridge/types.py
batch_bridge-0.0.1rc0.dist-info/METADATA
batch_bridge-0.0.1rc0.dist-info/WHEEL
batch_bridge-0.0.1rc0.dist-info/licenses/LICENSE
batch_bridge-0.0.1rc0.dist-info/RECORD
