Metadata-Version: 2.4
Name: batch-bridge
Version: 0.0.1rc0
Summary: Prebuilt utilities for memory management and retrieval.
License: MIT License
License-File: LICENSE
Requires-Python: >=3.11
Requires-Dist: langgraph-api>=0.0.33
Requires-Dist: langgraph>=0.2.66
